pdf_unannotate/__init__.py
pdf_unannotate/__main__.py
pdf_unannotate/pdf_unannotate.py
pdf_unannotate-0.99.9.dist-info/LICENSE
pdf_unannotate-0.99.9.dist-info/METADATA
pdf_unannotate-0.99.9.dist-info/WHEEL
pdf_unannotate-0.99.9.dist-info/entry_points.txt
pdf_unannotate-0.99.9.dist-info/top_level.txt
pdf_unannotate-0.99.9.dist-info/RECORD
