Metadata-Version: 2.1
Name: pdf-unannotate
Version: 0.99.9
Summary: Command line script to easily remove annotations from PDFs.
Author-email: Michael Wilson <mawilson@udel.edu>
Project-URL: Homepage, https://github.com/mawilson1234/pdf-unannotate
Keywords: pdf,PDF,PyPDF2,annotation
Classifier: Development Status :: 4 - Beta
Classifier: Programming Language :: Python
Classifier: Programming Language :: Python :: 3
Requires-Python: >=3
License-File: LICENSE
Requires-Dist: PyPDF2 >=3.0.1
Requires-Dist: tqdm >=4.66.5
